setup.py
custom_cli/__init__.py
custom_cli.egg-info/PKG-INFO
custom_cli.egg-info/SOURCES.txt
custom_cli.egg-info/dependency_links.txt
custom_cli.egg-info/not-zip-safe
custom_cli.egg-info/top_level.txt