Metadata-Version: 1.0
Name: custom-cli
Version: 0.1
Summary: Demo of custom cli
Home-page: https://gitlab.com/cicd-automation/custom_cli.git
Author: Long Ly
Author-email: lyhoanglong94@gmail.com
License: MIT
Platform: UNKNOWN
